kevin_toolbox/__init__.py
kevin_toolbox/computer_science/__init__.py
kevin_toolbox/computer_science/algorithm/__init__.py
kevin_toolbox/computer_science/algorithm/cache_manager/__init__.py
kevin_toolbox/computer_science/algorithm/cache_manager/cache_manager.py
kevin_toolbox/computer_science/algorithm/cache_manager/cache_manager_wto_strategy.py
kevin_toolbox/computer_science/algorithm/cache_manager/variable.py
kevin_toolbox/computer_science/algorithm/cache_manager/cache/__init__.py
kevin_toolbox/computer_science/algorithm/cache_manager/cache/array_cache.py
kevin_toolbox/computer_science/algorithm/cache_manager/cache/cache_base.py
kevin_toolbox/computer_science/algorithm/cache_manager/cache/memo_cache.py
kevin_toolbox/computer_science/algorithm/cache_manager/strategy/__init__.py
kevin_toolbox/computer_science/algorithm/cache_manager/strategy/fifo_strategy.py
kevin_toolbox/computer_science/algorithm/cache_manager/strategy/lfu_strategy.py
kevin_toolbox/computer_science/algorithm/cache_manager/strategy/lru_strategy.py
kevin_toolbox/computer_science/algorithm/cache_manager/strategy/lst_strategy.py
kevin_toolbox/computer_science/algorithm/cache_manager/strategy/strategy_base.py
kevin_toolbox/computer_science/algorithm/cache_manager/test/__init__.py
kevin_toolbox/computer_science/algorithm/cache_manager/test/test_cache_builder.py
kevin_toolbox/computer_science/algorithm/cache_manager/test/test_cache_manager.py
kevin_toolbox/computer_science/algorithm/cache_manager/test/test_cache_strategy.py
kevin_toolbox/computer_science/algorithm/combinatorial_optimization/__init__.py
kevin_toolbox/computer_science/algorithm/combinatorial_optimization/get_subset_with_largest_product.py
kevin_toolbox/computer_science/algorithm/combinatorial_optimization/zero_one_knapsack_problem.py
kevin_toolbox/computer_science/algorithm/combinatorial_optimization/test/__init__.py
kevin_toolbox/computer_science/algorithm/combinatorial_optimization/test/test_get_subset_with_largest_product.py
kevin_toolbox-1.4.14.dist-info/METADATA
kevin_toolbox-1.4.14.dist-info/WHEEL
kevin_toolbox-1.4.14.dist-info/top_level.txt
kevin_toolbox-1.4.14.dist-info/RECORD
