Metadata-Version: 2.1
Name: kevin-toolbox
Version: 1.4.14
Summary: 一个常用的工具代码包集合
Home-page: https://github.com/cantbeblank96/kevin_toolbox
Download-URL: https://github.com/username/your-package/archive/refs/tags/v1.0.0.tar.gz
Author: kevin hsu
Author-email: xukaiming1996@163.com
License: MIT
Keywords: mathematics,pytorch,numpy,machine-learning,algorithm
Platform: UNKNOWN
Classifier: License :: OSI Approved :: MIT License
Classifier: Programming Language :: Python
Classifier: Programming Language :: Python :: 3
Requires-Python: >=3.6
Requires-Dist: torch (>=1.2.0)
Requires-Dist: numpy (>=1.19.0)
Provides-Extra: plot
Requires-Dist: matplotlib (>=3.0) ; extra == 'plot'
Provides-Extra: rest
Requires-Dist: pytest (>=6.2.5) ; extra == 'rest'
Requires-Dist: line-profiler (>=3.5) ; extra == 'rest'
